cobyqa/__init__.py
cobyqa/framework.py
cobyqa/main.py
cobyqa/models.py
cobyqa/problem.py
cobyqa/settings.py
cobyqa/subsolvers/__init__.py
cobyqa/subsolvers/geometry.py
cobyqa/subsolvers/optim.py
cobyqa/tests/__init__.py
cobyqa/tests/test_main.py
cobyqa/tests/test_models.py
cobyqa/tests/test_problem.py
cobyqa/utils/__init__.py
cobyqa/utils/exceptions.py
cobyqa/utils/math.py
cobyqa/utils/versions.py
cobyqa/utils/tests/__init__.py
cobyqa/utils/tests/test_exceptions.py
cobyqa/utils/tests/test_math.py
cobyqa-1.1.1.dist-info/LICENSE
cobyqa-1.1.1.dist-info/METADATA
cobyqa-1.1.1.dist-info/WHEEL
cobyqa-1.1.1.dist-info/top_level.txt
cobyqa-1.1.1.dist-info/RECORD
