Metadata-Version: 2.1
Name: cobyqa
Version: 1.1.1
Summary: Constrained Optimization BY Quadratic Approximations
Author-email: "Tom M. Ragonneau and Zaikun Zhang" <cobyqa@python.org>
Maintainer-email: "Tom M. Ragonneau" <tom.ragonneau@polyu.edu.hk>, Zaikun Zhang <zaikun.zhang@polyu.edu.hk>
License: BSD 3-Clause License
Project-URL: homepage, https://www.cobyqa.com
Project-URL: documentation, https://www.cobyqa.com
Project-URL: source, https://github.com/cobyqa/cobyqa
Project-URL: download, https://pypi.org/project/cobyqa/#files
Project-URL: tracker, https://github.com/cobyqa/cobyqa/issues
Keywords: blackbox-optimization,constrained-optimization,derivative-free-optimization,hyperparameter-optimization,nonlinear-optimization,numerical-optimization,optimization,optimization-algorithms,optimization-methods,optimization-tools,simulation-based-optimization,unconstrained-optimization
Classifier: Development Status :: 5 - Production/Stable
Classifier: Intended Audience :: Developers
Classifier: Intended Audience :: Education
Classifier: Intended Audience :: Science/Research
Classifier: License :: OSI Approved :: BSD License
Classifier: Operating System :: OS Independent
Classifier: Programming Language :: Python
Classifier: Programming Language :: Python :: 3
Classifier: Programming Language :: Python :: 3 :: Only
Classifier: Programming Language :: Python :: 3.8
Classifier: Programming Language :: Python :: 3.9
Classifier: Programming Language :: Python :: 3.10
Classifier: Programming Language :: Python :: 3.11
Classifier: Programming Language :: Python :: 3.12
Classifier: Topic :: Scientific/Engineering
Classifier: Topic :: Scientific/Engineering :: Mathematics
Classifier: Topic :: Software Development
Requires-Python: >=3.8
License-File: LICENSE
Requires-Dist: numpy >=1.17.0
Requires-Dist: scipy >=1.10.0
Provides-Extra: doc
Requires-Dist: matplotlib ==3.8.3 ; extra == 'doc'
Requires-Dist: numpydoc ==1.6.0 ; extra == 'doc'
Requires-Dist: pydata-sphinx-theme ==0.15.2 ; extra == 'doc'
Requires-Dist: Sphinx ==7.2.6 ; extra == 'doc'
Requires-Dist: sphinx-copybutton ==0.5.2 ; extra == 'doc'
Requires-Dist: Sphinx-Substitution-Extensions ==2024.2.25 ; extra == 'doc'
Requires-Dist: sphinxcontrib-bibtex ==2.6.2 ; extra == 'doc'
Provides-Extra: examples
Requires-Dist: matplotlib ; extra == 'examples'
Provides-Extra: tests
Requires-Dist: pytest >=6.1.0 ; extra == 'tests'
Requires-Dist: pytest-cov ; extra == 'tests'
